binalyzer_vmf/__init__.py
binalyzer_vmf/cli.py
binalyzer_vmf/extension.py
binalyzer_vmf-1.0.0.data/data/CHANGELOG.md
binalyzer_vmf-1.0.0.dist-info/AUTHORS
binalyzer_vmf-1.0.0.dist-info/LICENSE.rst
binalyzer_vmf-1.0.0.dist-info/METADATA
binalyzer_vmf-1.0.0.dist-info/WHEEL
binalyzer_vmf-1.0.0.dist-info/entry_points.txt
binalyzer_vmf-1.0.0.dist-info/top_level.txt
binalyzer_vmf-1.0.0.dist-info/RECORD
