Metadata-Version: 2.1
Name: binalyzer-vmf
Version: 1.0.0
Summary: Binary Data Analyzer
Home-page: https://www.denisvasilik.com/binalyzer-vmf
Author: Denis Vasilìk
Author-email: contact@denisvasilik.com
License: UNKNOWN
Project-URL: Bug Tracker, https://github.com/denisvasilik/binalyzer-vmf/issues/
Project-URL: Documentation, https://binalyzer.readthedocs.io/en/latest/
Project-URL: Source Code, https://github.com/denisvasilik/binalyzer-vmf/
Platform: UNKNOWN
Classifier: Programming Language :: Python :: 3.6
Classifier: Operating System :: OS Independent
Requires-Dist: binalyzer
Requires-Dist: click (>=5.1)
